deeptransyt/__init__.py
deeptransyt/auxiliary_functions.py
deeptransyt/fetch_metabolites.py
deeptransyt/main.py
deeptransyt/make_predictions.py
deeptransyt/models.py
deeptransyt/reactions_generator.py
deeptransyt/sequence_processing.py
deeptransyt-0.0.13.dist-info/LICENSE.txt
deeptransyt-0.0.13.dist-info/METADATA
deeptransyt-0.0.13.dist-info/WHEEL
deeptransyt-0.0.13.dist-info/entry_points.txt
deeptransyt-0.0.13.dist-info/top_level.txt
deeptransyt-0.0.13.dist-info/RECORD
