Metadata-Version: 2.2
Name: deeptransyt
Version: 0.0.13
Summary: Transporters annotation using LLM's
Home-page: https://github.com/Apolinario8/deeptransyt
Author: Gonçalo Apolinário Cardoso
Author-email: goncalocardoso2016@gmail.com
License: MIT
Requires-Python: >=3.8
License-File: LICENSE.txt
Requires-Dist: Bio==1.6.2
Requires-Dist: numpy==1.24.4
Requires-Dist: pandas==2.0.3
Requires-Dist: pytorch_lightning==2.4.0
Requires-Dist: torch==2.4.1
Requires-Dist: transformers==4.46.3
Dynamic: author
Dynamic: author-email
Dynamic: description
Dynamic: description-content-type
Dynamic: home-page
Dynamic: license
Dynamic: requires-dist
Dynamic: requires-python
Dynamic: summary
